eda_fe_model/__init__.py
eda_fe_model/package.py
eda_fe_model-0.3.2.dist-info/LICENSE.txt
eda_fe_model-0.3.2.dist-info/METADATA
eda_fe_model-0.3.2.dist-info/WHEEL
eda_fe_model-0.3.2.dist-info/top_level.txt
eda_fe_model-0.3.2.dist-info/RECORD
