Metadata-Version: 2.1
Name: eda-fe-model
Version: 0.3.2
Summary: A python package to handle EDA and feature extraction and also return the best hyperparameters for a tabular classification problem.
Home-page: https://github.com/Akkimehr/eda-fe-model
Author: ['Akshat Mehrotra', 'Mohammad Shaheer Khan']
Author-email: akshat117@gmail.com
License: MIT
Keywords: EDA,Feature_selection,Model_hyper_parametrs
Platform: UNKNOWN
Requires-Dist: numpy (>=1.18.5)
Requires-Dist: pandas (>=1.0.5)
Requires-Dist: scikit-learn (>=0.23.1)
Requires-Dist: statsmodels (>=0.11.1)
Requires-Dist: tensorflow (>=2.1.0)
